{"destination_addresses": ["Montgomery, AL, USA", "Phoenix, AZ, USA", "Little Rock, AR, USA", "Sacramento, CA, USA", "Denver, CO, USA", "Hartford, CT, USA", "Dover, DE, USA", "Washington, DC, USA", "Tallahassee, FL, USA", "Atlanta, GA, USA", "Boise, ID, USA", "Springfield, IL, USA", "Indianapolis, IN, USA", "Des Moines, IA, USA", "Topeka, KS, USA", "Frankfort, KY 40601, USA", "Baton Rouge, LA, USA", "Augusta, ME 04330, USA", "Annapolis, MD, USA", "Boston, MA, USA", "Lansing, MI, USA", "St Paul, MN, USA", "Jackson, MS, USA", "Jefferson City, MO, USA", "Helena, MT, USA", "Lincoln, NE, USA", "Carson City, NV, USA", "Concord, NH, USA", "Trenton, NJ, USA", "Santa Fe, NM, USA", "Albany, NY, USA", "Raleigh, NC, USA", "Bismarck, ND, USA", "Columbus, OH, USA", "Oklahoma City, OK, USA", "Salem, OR, USA", "Harrisburg, PA, USA", "Providence, RI, USA", "Columbia, SC, USA", "Pierre, SD 57501, USA", "Nashville, TN, USA", "Austin, TX, USA", "Salt Lake City, UT, USA", "Montpelier, VT 05602, USA", "Richmond, VA, USA", "Olympia, WA, USA", "Charleston, WV, USA", "Madison, WI, USA", "Cheyenne, WY, USA"], "origin_addresses": ["Frankfort, KY 40601, USA"], "status": "OK", "rows": [{"elements": [{"status": "OK", "distance": {"text": "789 km", "value": 789240}, "duration": {"text": "7 hours 11 mins", "value": 25831}}, {"status": "OK", "distance": {"text": "2,848 km", "value": 2847761}, "duration": {"text": "1 day 2 hours", "value": 92919}}, {"status": "OK", "distance": {"text": "894 km", "value": 893599}, "duration": {"text": "8 hours 14 mins", "value": 29640}}, {"status": "OK", "distance": {"text": "3,667 km", "value": 3667353}, "duration": {"text": "1 day 9 hours", "value": 119181}}, {"status": "OK", "distance": {"text": "1,871 km", "value": 1870680}, "duration": {"text": "16 hours 42 mins", "value": 60133}}, {"status": "OK", "distance": {"text": "1,376 km", "value": 1375631}, "duration": {"text": "12 hours 47 mins", "value": 45999}}, {"status": "OK", "distance": {"text": "1,033 km", "value": 1033321}, "duration": {"text": "9 hours 44 mins", "value": 35063}}, {"status": "OK", "distance": {"text": "900 km", "value": 900104}, "duration": {"text": "8 hours 27 mins", "value": 30396}}, {"status": "OK", "distance": {"text": "1,076 km", "value": 1076235}, "duration": {"text": "10 hours 16 mins", "value": 36974}}, {"status": "OK", "distance": {"text": "657 km", "value": 657024}, "duration": {"text": "6 hours 3 mins", "value": 21776}}, {"status": "OK", "distance": {"text": "3,116 km", "value": 3116441}, "duration": {"text": "1 day 4 hours", "value": 100546}}, {"status": "OK", "distance": {"text": "603 km", "value": 602598}, "duration": {"text": "5 hours 39 mins", "value": 20349}}, {"status": "OK", "distance": {"text": "265 km", "value": 265452}, "duration": {"text": "2 hours 37 mins", "value": 9447}}, {"status": "OK", "distance": {"text": "1,027 km", "value": 1027365}, "duration": {"text": "9 hours 23 mins", "value": 33793}}, {"status": "OK", "distance": {"text": "1,001 km", "value": 1001207}, "duration": {"text": "9 hours 11 mins", "value": 33088}}, {"status": "OK", "distance": {"text": "1 m", "value": 0}, "duration": {"text": "1 min", "value": 0}}, {"status": "OK", "distance": {"text": "1,280 km", "value": 1280198}, "duration": {"text": "11 hours 35 mins", "value": 41720}}, {"status": "OK", "distance": {"text": "1,773 km", "value": 1773452}, "duration": {"text": "16 hours 30 mins", "value": 59383}}, {"status": "OK", "distance": {"text": "935 km", "value": 935323}, "duration": {"text": "8 hours 36 mins", "value": 30947}}, {"status": "OK", "distance": {"text": "1,528 km", "value": 1527611}, "duration": {"text": "14 hours 18 mins", "value": 51476}}, {"status": "OK", "distance": {"text": "666 km", "value": 666204}, "duration": {"text": "6 hours 10 mins", "value": 22204}}, {"status": "OK", "distance": {"text": "1,213 km", "value": 1212839}, "duration": {"text": "11 hours 11 mins", "value": 40244}}, {"status": "OK", "distance": {"text": "1,000 km", "value": 1000439}, "duration": {"text": "9 hours 4 mins", "value": 32619}}, {"status": "OK", "distance": {"text": "714 km", "value": 714140}, "duration": {"text": "6 hours 38 mins", "value": 23884}}, {"status": "OK", "distance": {"text": "2,898 km", "value": 2898489}, "duration": {"text": "1 day 2 hours", "value": 94701}}, {"status": "OK", "distance": {"text": "1,212 km", "value": 1212115}, "duration": {"text": "11 hours 20 mins", "value": 40811}}, {"status": "OK", "distance": {"text": "3,482 km", "value": 3482041}, "duration": {"text": "1 day 8 hours", "value": 113570}}, {"status": "OK", "distance": {"text": "1,514 km", "value": 1514046}, "duration": {"text": "14 hours 54 mins", "value": 53620}}, {"status": "OK", "distance": {"text": "1,091 km", "value": 1091120}, "duration": {"text": "10 hours 9 mins", "value": 36523}}, {"status": "OK", "distance": {"text": "2,163 km", "value": 2163393}, "duration": {"text": "19 hours 26 mins", "value": 69989}}, {"status": "OK", "distance": {"text": "1,282 km", "value": 1281661}, "duration": {"text": "11 hours 59 mins", "value": 43158}}, {"status": "OK", "distance": {"text": "832 km", "value": 831847}, "duration": {"text": "7 hours 52 mins", "value": 28321}}, {"status": "OK", "distance": {"text": "1,908 km", "value": 1907693}, "duration": {"text": "17 hours 16 mins", "value": 62188}}, {"status": "OK", "distance": {"text": "299 km", "value": 298695}, "duration": {"text": "3 hours 4 mins", "value": 11059}}, {"status": "OK", "distance": {"text": "1,305 km", "value": 1305104}, "duration": {"text": "11 hours 47 mins", "value": 42438}}, {"status": "OK", "distance": {"text": "3,867 km", "value": 3866560}, "duration": {"text": "1 day 11 hours", "value": 126238}}, {"status": "OK", "distance": {"text": "906 km", "value": 906063}, "duration": {"text": "8 hours 20 mins", "value": 29985}}, {"status": "OK", "distance": {"text": "1,475 km", "value": 1474884}, "duration": {"text": "13 hours 45 mins", "value": 49509}}, {"status": "OK", "distance": {"text": "739 km", "value": 738675}, "duration": {"text": "6 hours 52 mins", "value": 24744}}, {"status": "OK", "distance": {"text": "1,814 km", "value": 1813796}, "duration": {"text": "16 hours 22 mins", "value": 58918}}, {"status": "OK", "distance": {"text": "338 km", "value": 338365}, "duration": {"text": "3 hours 15 mins", "value": 11710}}, {"status": "OK", "distance": {"text": "1,715 km", "value": 1715283}, "duration": {"text": "15 hours 38 mins", "value": 56254}}, {"status": "OK", "distance": {"text": "2,632 km", "value": 2632023}, "duration": {"text": "23 hours 53 mins", "value": 86004}}, {"status": "OK", "distance": {"text": "1,492 km", "value": 1492156}, "duration": {"text": "14 hours 40 mins", "value": 52782}}, {"status": "OK", "distance": {"text": "829 km", "value": 828701}, "duration": {"text": "7 hours 40 mins", "value": 27581}}, {"status": "OK", "distance": {"text": "3,897 km", "value": 3896867}, "duration": {"text": "1 day 11 hours", "value": 127289}}, {"status": "OK", "distance": {"text": "319 km", "value": 319281}, "duration": {"text": "2 hours 59 mins", "value": 10756}}, {"status": "OK", "distance": {"text": "803 km", "value": 803114}, "duration": {"text": "7 hours 37 mins", "value": 27439}}, {"status": "OK", "distance": {"text": "1,928 km", "value": 1928224}, "duration": {"text": "17 hours 32 mins", "value": 63099}}]}]}